test1.py
pytransform/__init__.py
testing_crypto_1-0.6.6.dist-info/METADATA
testing_crypto_1-0.6.6.dist-info/WHEEL
testing_crypto_1-0.6.6.dist-info/top_level.txt
testing_crypto_1-0.6.6.dist-info/RECORD
