Metadata-Version: 2.1
Name: testing-crypto-1
Version: 0.6.6
Summary: Crypting code
Home-page: UNKNOWN
Author: Pranav Chandran
Author-email: pranav.chandran@gmail.com
License: UNKNOWN
Platform: UNKNOWN
Classifier: Programming Language :: Python :: 3
Classifier: License :: OSI Approved :: MIT License
Classifier: Operating System :: OS Independent
Requires-Python: >=3.6
Requires-Dist: pyarmor
